{
	"info": {
		"_postman_id": "1711e2fc-0f13-423f-aeeb-9e15732d558a",
		"name": "Senai.Peoples.Tarde",
		"schema": "https://schema.getpostman.com/json/collection/v2.1.0/collection.json"
	},
	"item": [
		{
			"name": "Funcionario.ListarTodos",
			"protocolProfileBehavior": {
				"disableBodyPruning": true
			},
			"request": {
				"method": "GET",
				"header": [
					{
						"key": "Content-Type",
						"name": "Content-Type",
						"value": "application/json",
						"type": "text"
					}
				],
				"body": {
					"mode": "raw",
					"raw": "{\n\t\"idestilosmusical\" : 12,\n\t\"nome\" : \"afdf\"\n\t\n}"
				},
				"url": {
					"raw": "http://localhost:5000/api/Funcionario",
					"protocol": "http",
					"host": [
						"localhost"
					],
					"port": "5000",
					"path": [
						"api",
						"Funcionario"
					]
				}
			},
			"response": []
		},
		{
			"name": "Funcionario.BuscarPorId",
			"request": {
				"method": "GET",
				"header": [],
				"url": {
					"raw": "http://localhost:5000/api/Funcionario/2",
					"protocol": "http",
					"host": [
						"localhost"
					],
					"port": "5000",
					"path": [
						"api",
						"Funcionario",
						"2"
					]
				}
			},
			"response": []
		},
		{
			"name": "Funcionario.CadastrarPorJSON",
			"request": {
				"method": "POST",
				"header": [
					{
						"key": "Content-Type",
						"name": "Content-Type",
						"value": "application/json",
						"type": "text"
					}
				],
				"body": {
					"mode": "raw",
					"raw": "{\n\t\"nome\" : \"Gabriel\",\n\t\"sobrenome\" : \"Amador\"\n}"
				},
				"url": {
					"raw": "http://localhost:5000/api/Funcionario",
					"protocol": "http",
					"host": [
						"localhost"
					],
					"port": "5000",
					"path": [
						"api",
						"Funcionario"
					]
				}
			},
			"response": []
		},
		{
			"name": "Funcionario.DeletarPorId",
			"request": {
				"method": "DELETE",
				"header": [],
				"url": {
					"raw": "http://localhost:5000/api/Funcionario/5",
					"protocol": "http",
					"host": [
						"localhost"
					],
					"port": "5000",
					"path": [
						"api",
						"Funcionario",
						"5"
					]
				}
			},
			"response": []
		},
		{
			"name": "Funcionario.AtualizarPorIdAndJSON",
			"request": {
				"method": "PUT",
				"header": [
					{
						"key": "Content-Type",
						"name": "Content-Type",
						"value": "application/json",
						"type": "text"
					}
				],
				"body": {
					"mode": "raw",
					"raw": "{\n\t\"nome\":\"Gabriel\",\n\t\"sobrenome\":\"Rodrigues\"\n}"
				},
				"url": {
					"raw": "http://localhost:5000/api/Funcionario/4",
					"protocol": "http",
					"host": [
						"localhost"
					],
					"port": "5000",
					"path": [
						"api",
						"Funcionario",
						"4"
					]
				}
			},
			"response": []
		}
	]
}